fiction_outlines/__init__.py
fiction_outlines/admin.py
fiction_outlines/apps.py
fiction_outlines/forms.py
fiction_outlines/models.py
fiction_outlines/receivers.py
fiction_outlines/rules.py
fiction_outlines/signals.py
fiction_outlines/urls.py
fiction_outlines/views.py
fiction_outlines/migrations/0001_initial.py
fiction_outlines/migrations/0002_auto_20180407_2137.py
fiction_outlines/migrations/0003_auto_20180414_2035.py
fiction_outlines/migrations/0004_auto_20180419_1154.py
fiction_outlines/migrations/__init__.py
fiction_outlines/static/css/fiction_outlines.css
fiction_outlines/static/js/fiction_outlines.js
fiction_outlines/templates/fiction_outlines/arc_create.html
fiction_outlines/templates/fiction_outlines/arc_delete.html
fiction_outlines/templates/fiction_outlines/arc_detail.html
fiction_outlines/templates/fiction_outlines/arc_list.html
fiction_outlines/templates/fiction_outlines/arc_update.html
fiction_outlines/templates/fiction_outlines/arcnode_create.html
fiction_outlines/templates/fiction_outlines/arcnode_delete.html
fiction_outlines/templates/fiction_outlines/arcnode_detail.html
fiction_outlines/templates/fiction_outlines/arcnode_move.html
fiction_outlines/templates/fiction_outlines/arcnode_update.html
fiction_outlines/templates/fiction_outlines/base.html
fiction_outlines/templates/fiction_outlines/character_create.html
fiction_outlines/templates/fiction_outlines/character_delete.html
fiction_outlines/templates/fiction_outlines/character_detail.html
fiction_outlines/templates/fiction_outlines/character_instance_create.html
fiction_outlines/templates/fiction_outlines/character_instance_delete.html
fiction_outlines/templates/fiction_outlines/character_instance_detail.html
fiction_outlines/templates/fiction_outlines/character_instance_list.html
fiction_outlines/templates/fiction_outlines/character_instance_update.html
fiction_outlines/templates/fiction_outlines/character_list.html
fiction_outlines/templates/fiction_outlines/character_update.html
django_fiction_outlines-0.4.0.dist-info/AUTHORS.rst
django_fiction_outlines-0.4.0.dist-info/LICENSE
django_fiction_outlines-0.4.0.dist-info/METADATA
django_fiction_outlines-0.4.0.dist-info/WHEEL
django_fiction_outlines-0.4.0.dist-info/top_level.txt
django_fiction_outlines-0.4.0.dist-info/RECORD
