Metadata-Version: 2.1
Name: django-fiction-outlines
Version: 0.4.0
Summary: A reusable Django app for managing fiction outlines. Part of the broader maceoutliner project.
Home-page: https://github.com/maceoutliner/django-fiction-outlines
Author: Daniel Andrlik
Author-email: daniel@andrlik.org
License: BSD
Project-URL: Documentation, http://django-fiction-outlines.readthedocs.io/en/latest/index.html
Project-URL: Source, https://github.com/maceoutliner/django-fiction-outlines/
Project-URL: Issue Tracker, https://github.com/maceoutliner/django-fiction-outlines/issues
Keywords: django-fiction-outlines
Platform: UNKNOWN
Classifier: Development Status :: 3 - Alpha
Classifier: Framework :: Django
Classifier: Intended Audience :: Developers
Classifier: License :: OSI Approved :: BSD License
Classifier: Natural Language :: English
Classifier: Programming Language :: Python :: 3.9
Classifier: Programming Language :: Python :: 3.10
Requires-Python: ~=3.6
License-File: LICENSE
License-File: AUTHORS.rst
Requires-Dist: django-braces (>=1.15.0)
Requires-Dist: django-model-utils (>=4.2.0)
Requires-Dist: django-taggit (>=2.1.0)
Requires-Dist: django-treebeard (>=4.5.1)
Requires-Dist: django (>=3.2.12)
Requires-Dist: pytz
Requires-Dist: rules (>=3.2.1)
